listless/__about__.py
listless/__init__.py
listless/__main__.py
listless/py.typed
listless-0.4.1.dist-info/WHEEL
listless-0.4.1.dist-info/METADATA
listless-0.4.1.dist-info/RECORD
