Metadata-Version: 2.3
Name: listless
Version: 0.4.1
Summary: generator utils; aka listless
Keywords: dgpy,generators,itertools,typed
Author: jesse
Author-email: jesse <jesse@dgi.com>
License: MIT
Classifier: Development Status :: 5 - Production/Stable
Classifier: Intended Audience :: Developers
Classifier: License :: OSI Approved :: MIT License
Classifier: Programming Language :: Python
Classifier: Programming Language :: Python :: 3 :: Only
Classifier: Programming Language :: Python :: 3.11
Classifier: Programming Language :: Python :: 3.12
Classifier: Programming Language :: Python :: 3.13
Classifier: Programming Language :: Python :: 3.14
Classifier: Typing :: Typed
Requires-Python: >=3.11, <4.0
Project-URL: homepage, https://github.com/dynamic-graphics-inc/dgpy-libs/tree/main/libs/listless
Project-URL: repository, https://github.com/dynamic-graphics-inc/dgpy-libs
